{"slug":"protests-and-marches-letting-the-police-know","updated_at":"2012-01-20T12:38:55+00:00","alternative_title":"","body":"$!By law you must tell the police in writing 6 days before a public march if you're the organiser$!\r\n\r\n[Tell the police](http://www.police.uk/?view=force_sites \"Find a police force\"){:rel=\"external\"} the:\r\n\r\n- date and time of the march\r\n- route\r\n- expected number of people\r\n\r\nThe police have the power to:\r\n\r\n- limit or change the route of your march\r\n- ban it altogether\r\n\r\n^If you arrange the march at short notice, you must still tell the police as soon as you can^\r\n\r\n##If there's no march involved\r\n\r\nIf there's no march, you don't have to tell the police, but it's still a good idea. \r\n\r\nThe police can change the location and limit how long a rally lasts. They can stop a sit-down protest if it blocks road traffic or public walkways.","overview":"Organising a march, rally or demonstration - when you do, and don't have to contact the police before the event.","title":"Protests and marches: letting the police know","type":"answer"}
