{"slug":"homelessness-help-from-council","updated_at":"2012-01-26T15:39:37+00:00","alternative_title":"","introduction":"Check what help and advice your council can provide if you are homeless or about to lose your home. Enter your postcode to find your council's website for more information.","minutes_to_complete":"","more_information":"","overview":"Check what help and advice your council can provide if you are homeless or about to lose your home","title":"Apply for emergency housing from your council","expectations":[{"table":{"css_class":"england_only","text":"Available in England only"}}],"type":"local_transaction","council":false}
